micromechanics_indentationGUI/AnalysePopIn.py
micromechanics_indentationGUI/CalculateHardnessModulus.py
micromechanics_indentationGUI/CalibrateTAF.py
micromechanics_indentationGUI/Classification.py
micromechanics_indentationGUI/CorrectThermalDrift.py
micromechanics_indentationGUI/DaoMethod.py
micromechanics_indentationGUI/DialogAbout_ui.py
micromechanics_indentationGUI/DialogError_ui.py
micromechanics_indentationGUI/DialogExport_ui.py
micromechanics_indentationGUI/DialogOpen_ui.py
micromechanics_indentationGUI/DialogSaveAs_ui.py
micromechanics_indentationGUI/DialogWait_ui.py
micromechanics_indentationGUI/Export.py
micromechanics_indentationGUI/FrameStiffness.py
micromechanics_indentationGUI/H_over_reE_vs_Wp_over_wt_Cheng1998.py
micromechanics_indentationGUI/Save_and_Load.py
micromechanics_indentationGUI/TipRadius.py
micromechanics_indentationGUI/Tools4hdf5.py
micromechanics_indentationGUI/WaitingUpgrade_of_micromechanics.py
micromechanics_indentationGUI/__init__.py
micromechanics_indentationGUI/calibration_iterativeMethod.py
micromechanics_indentationGUI/load_depth.py
micromechanics_indentationGUI/logo.py
micromechanics_indentationGUI/main.py
micromechanics_indentationGUI/main_window_ui.py
micromechanics_indentationGUI/Examples/Example1/FusedSilica.xlsx
micromechanics_indentationGUI/Examples/Example2/Tungsten_FrameStiffness.xlsx
micromechanics_indentationGUI/Examples/Example2/Tungsten_TipRadius.xlsx
micromechanics_indentationGUI/Examples/Example3/FusedSilica_CSM.xlsx
micromechanics_indentationGUI/pic/QRcode_generate.py
micromechanics_indentationGUI/pic/indentationGUI_QRcode.png
micromechanics_indentationGUI/pic/logo.png
micromechanics_indentationGUI/pic/logo2.png
micromechanics_indentationGUI/pic/logo_16x16.png
micromechanics_indentationGUI/pic/logo_24x24.png
micromechanics_indentationGUI/pic/logo_256x256.png
micromechanics_indentationGUI/pic/logo_32x32.png
micromechanics_indentationGUI/pic/logo_48x48.png
micromechanics_indentationGUI-0.1.33.dist-info/METADATA
micromechanics_indentationGUI-0.1.33.dist-info/WHEEL
micromechanics_indentationGUI-0.1.33.dist-info/entry_points.txt
micromechanics_indentationGUI-0.1.33.dist-info/top_level.txt
micromechanics_indentationGUI-0.1.33.dist-info/RECORD
