Metadata-Version: 2.2
Name: micromechanics-indentationGUI
Version: 0.1.33
Summary: GUI for nanoindentation data
Home-page: https://micromechanics.github.io/indentationGUI/
Author: Micromechanics Team and Weiguang Yang
Author-email: sbrinckm@gmail.com
Classifier: Programming Language :: Python
Classifier: License :: OSI Approved :: BSD License
Classifier: Programming Language :: Python :: 3
Requires-Dist: pyside6==6.4.2
Requires-Dist: numpy
Requires-Dist: matplotlib>=3.6.3
Requires-Dist: micromechanics==1.1.14
Requires-Dist: pandas==1.4.2
Requires-Dist: openpyxl>=3.1.1
Requires-Dist: scikit-learn
Requires-Dist: tables
Requires-Dist: xlsxwriter==3.1.2
